setup.py
redis_s3_backup/__init__.py
redis_s3_backup/command_line.py
redis_s3_backup.egg-info/PKG-INFO
redis_s3_backup.egg-info/SOURCES.txt
redis_s3_backup.egg-info/dependency_links.txt
redis_s3_backup.egg-info/entry_points.txt
redis_s3_backup.egg-info/not-zip-safe
redis_s3_backup.egg-info/requires.txt
redis_s3_backup.egg-info/top_level.txt