Metadata-Version: 1.0
Name: redis-s3-backup
Version: 0.2
Summary: Backup Redis rdb dump file to AWS S3
Home-page: https://github.com/arpith/Redis-S3-Backup
Author: Arpith Siromoney
Author-email: arpith@feedreader.co
License: MIT
Platform: UNKNOWN
